shadowlink/__init__.py
shadowlink/__main__.py
shadowlink/shadowlink.py
shadowlink/version.py
shadowlink-0.0.1.dist-info/licenses/LICENSE
shadowlink-0.0.1.dist-info/METADATA
shadowlink-0.0.1.dist-info/WHEEL
shadowlink-0.0.1.dist-info/entry_points.txt
shadowlink-0.0.1.dist-info/top_level.txt
shadowlink-0.0.1.dist-info/RECORD
