Metadata-Version: 2.4
Name: shadowlink
Version: 0.0.1
Summary: Ultimate URL Cloaking Tool — mask URLs behind trusted domains
Author-email: HErl <petherl@protonmail.com>
License: MIT
Keywords: url-shortener,cloaking,security,cli
Classifier: Programming Language :: Python :: 3.10
Classifier: License :: OSI Approved :: MIT License
Classifier: Operating System :: OS Independent
Requires-Python: >=3.10
License-File: LICENSE
Requires-Dist: pyshorteners==1.0.1
Provides-Extra: dev
Requires-Dist: pytest; extra == "dev"
Dynamic: license-file
